{
  "id": "chunk-2026-02-10-2c703397",
  "content": "Uses RLM-based memory system with JSON chunks and graph linking",
  "tokens": 12,
  "type": "fact",
  "metadata": {
    "created": "2026-02-10T22:09:13.817728Z",
    "conversation_id": "project-knowledge",
    "source": "interaction",
    "confidence": 0.95,
    "access_count": 23,
    "last_accessed": "2026-02-11T03:46:54.825897Z"
  },
  "links": {
    "context_of": [
      "chunk-2026-02-10-222d1698",
      "chunk-2026-02-10-f5afd75a",
      "chunk-2026-02-10-6225b28f",
      "chunk-2026-02-10-2a6b6d9f",
      "chunk-2026-02-10-e1497811",
      "chunk-2026-02-10-fd1a83b7",
      "chunk-2026-02-10-182464c2",
      "chunk-2026-02-10-a955b434",
      "chunk-2026-02-10-6fbafa51",
      "chunk-2026-02-10-a71054e2",
      "chunk-2026-02-10-58f0d8a5",
      "chunk-2026-02-10-96df1b08",
      "chunk-2026-02-10-9ae3167c"
    ],
    "follows": [
      "chunk-2026-02-10-222d1698",
      "chunk-2026-02-10-f5afd75a",
      "chunk-2026-02-10-6225b28f",
      "chunk-2026-02-10-2a6b6d9f",
      "chunk-2026-02-10-e1497811",
      "chunk-2026-02-10-fd1a83b7",
      "chunk-2026-02-10-182464c2",
      "chunk-2026-02-10-a955b434"
    ],
    "related_to": [
      "chunk-2026-02-10-31f08775",
      "chunk-2026-02-11-a11c8894",
      "chunk-2026-02-11-28f9a142",
      "chunk-2026-02-11-4fdbb770"
    ],
    "supports": [],
    "contradicts": []
  },
  "tags": [
    "architecture",
    "memory",
    "rlm"
  ]
}